pMTnet_Omni_Document/__init__.py
pMTnet_Omni_Document/__main__.py
pMTnet_Omni_Document/data_curation.py
pMTnet_Omni_Document/validation_data/human_alpha.txt
pMTnet_Omni_Document/validation_data/human_beta.txt
pMTnet_Omni_Document/validation_data/mouse_alpha.txt
pMTnet_Omni_Document/validation_data/mouse_beta.txt
pMTnet_Omni_Document/validation_data/valid_mhc.txt
pMTnet_Omni_Document-0.0.16.dist-info/LICENSE
pMTnet_Omni_Document-0.0.16.dist-info/METADATA
pMTnet_Omni_Document-0.0.16.dist-info/WHEEL
pMTnet_Omni_Document-0.0.16.dist-info/top_level.txt
pMTnet_Omni_Document-0.0.16.dist-info/RECORD
