Metadata-Version: 2.1
Name: pMTnet-Omni-Document
Version: 0.0.16
Summary: Document for pMTnet Omni
Author: Yi Han, Yuqiu Yang, Tao Wang
Author-email: yi.han@utsouthwestern.edu, yuqiuy@smu.edu, Tao.Wang@UTSouthwestern.edu
Classifier: Programming Language :: Python :: 3 :: Only
Classifier: Natural Language :: English
Classifier: Intended Audience :: Science/Research
Requires-Python: >=3.9,<3.11
License-File: LICENSE
Requires-Dist: numpy (==1.22.4)
Requires-Dist: pandas (==1.5.2)
Requires-Dist: tqdm (==4.64.1)
Requires-Dist: torch (==1.13.1)
Requires-Dist: fair-esm (==2.0.0)
